[
  {
    "name": null,
    "methods": [
      "POST"
    ],
    "paramNames": [],
    "path": "/login.do",
    "regexp": "/^\\/login\\.do(?:\\/(?=$))?$/",
    "stack": [
      "wrappedController"
    ]
  },
  {
    "name": null,
    "methods": [
      "POST"
    ],
    "paramNames": [],
    "path": "/registered.do",
    "regexp": "/^\\/registered\\.do(?:\\/(?=$))?$/",
    "stack": [
      "wrappedController"
    ]
  },
  {
    "name": null,
    "methods": [
      "HEAD",
      "GET"
    ],
    "paramNames": [],
    "path": "/showAllShops.do",
    "regexp": "/^\\/showAllShops\\.do(?:\\/(?=$))?$/",
    "stack": [
      "wrappedController"
    ]
  },
  {
    "name": null,
    "methods": [
      "POST"
    ],
    "paramNames": [],
    "path": "/uploadFile.do",
    "regexp": "/^\\/uploadFile\\.do(?:\\/(?=$))?$/",
    "stack": [
      "wrappedController"
    ]
  },
  {
    "name": null,
    "methods": [
      "POST"
    ],
    "paramNames": [],
    "path": "/uploadCandyFile.do",
    "regexp": "/^\\/uploadCandyFile\\.do(?:\\/(?=$))?$/",
    "stack": [
      "wrappedController"
    ]
  },
  {
    "name": null,
    "methods": [
      "POST"
    ],
    "paramNames": [],
    "path": "/admlogin.do",
    "regexp": "/^\\/admlogin\\.do(?:\\/(?=$))?$/",
    "stack": [
      "wrappedController"
    ]
  },
  {
    "name": null,
    "methods": [
      "HEAD",
      "GET"
    ],
    "paramNames": [],
    "path": "/showAll.do",
    "regexp": "/^\\/showAll\\.do(?:\\/(?=$))?$/",
    "stack": [
      "wrappedController"
    ]
  },
  {
    "name": null,
    "methods": [
      "HEAD",
      "GET"
    ],
    "paramNames": [],
    "path": "/delById.do",
    "regexp": "/^\\/delById\\.do(?:\\/(?=$))?$/",
    "stack": [
      "wrappedController"
    ]
  },
  {
    "name": null,
    "methods": [
      "POST"
    ],
    "paramNames": [],
    "path": "/updateName.do",
    "regexp": "/^\\/updateName\\.do(?:\\/(?=$))?$/",
    "stack": [
      "wrappedController"
    ]
  },
  {
    "name": null,
    "methods": [
      "HEAD",
      "GET"
    ],
    "paramNames": [],
    "path": "/showAllCandys.do",
    "regexp": "/^\\/showAllCandys\\.do(?:\\/(?=$))?$/",
    "stack": [
      "wrappedController"
    ]
  },
  {
    "name": null,
    "methods": [
      "POST"
    ],
    "paramNames": [],
    "path": "/updateCandys.do",
    "regexp": "/^\\/updateCandys\\.do(?:\\/(?=$))?$/",
    "stack": [
      "wrappedController"
    ]
  },
  {
    "name": null,
    "methods": [
      "HEAD",
      "GET"
    ],
    "paramNames": [],
    "path": "/delByCandyId.do",
    "regexp": "/^\\/delByCandyId\\.do(?:\\/(?=$))?$/",
    "stack": [
      "wrappedController"
    ]
  },
  {
    "name": null,
    "methods": [
      "POST"
    ],
    "paramNames": [],
    "path": "/uploadNutFile.do",
    "regexp": "/^\\/uploadNutFile\\.do(?:\\/(?=$))?$/",
    "stack": [
      "wrappedController"
    ]
  },
  {
    "name": null,
    "methods": [
      "HEAD",
      "GET"
    ],
    "paramNames": [],
    "path": "/showAllNuts.do",
    "regexp": "/^\\/showAllNuts\\.do(?:\\/(?=$))?$/",
    "stack": [
      "wrappedController"
    ]
  },
  {
    "name": null,
    "methods": [
      "POST"
    ],
    "paramNames": [],
    "path": "/updateNuts.do",
    "regexp": "/^\\/updateNuts\\.do(?:\\/(?=$))?$/",
    "stack": [
      "wrappedController"
    ]
  },
  {
    "name": null,
    "methods": [
      "HEAD",
      "GET"
    ],
    "paramNames": [],
    "path": "/delByNutsId.do",
    "regexp": "/^\\/delByNutsId\\.do(?:\\/(?=$))?$/",
    "stack": [
      "wrappedController"
    ]
  }
]